<annotation>
	<folder>JPEGImages</folder>
	<filename>1314.jpg</filename>
	<path>C:\Users\Breeze\Desktop\keras-yolo3-master\VOCdevkit\VOC2020\JPEGImages\1314.jpg</path>
	<source>
		<database>Unknown</database>
	</source>
	<size>
		<width>550</width>
		<height>309</height>
		<depth>3</depth>
	</size>
	<segmented>0</segmented>
	<object>
		<name>no-mask</name>
		<pose>Unspecified</pose>
		<truncated>0</truncated>
		<difficult>0</difficult>
		<bndbox>
			<xmin>6</xmin>
			<ymin>105</ymin>
			<xmax>55</xmax>
			<ymax>170</ymax>
		</bndbox>
	</object>
	<object>
		<name>no-mask</name>
		<pose>Unspecified</pose>
		<truncated>0</truncated>
		<difficult>0</difficult>
		<bndbox>
			<xmin>39</xmin>
			<ymin>192</ymin>
			<xmax>88</xmax>
			<ymax>257</ymax>
		</bndbox>
	</object>
	<object>
		<name>no-mask</name>
		<pose>Unspecified</pose>
		<truncated>0</truncated>
		<difficult>0</difficult>
		<bndbox>
			<xmin>134</xmin>
			<ymin>234</ymin>
			<xmax>183</xmax>
			<ymax>299</ymax>
		</bndbox>
	</object>
	<object>
		<name>no-mask</name>
		<pose>Unspecified</pose>
		<truncated>0</truncated>
		<difficult>0</difficult>
		<bndbox>
			<xmin>250</xmin>
			<ymin>203</ymin>
			<xmax>299</xmax>
			<ymax>268</ymax>
		</bndbox>
	</object>
	<object>
		<name>no-mask</name>
		<pose>Unspecified</pose>
		<truncated>0</truncated>
		<difficult>0</difficult>
		<bndbox>
			<xmin>278</xmin>
			<ymin>44</ymin>
			<xmax>327</xmax>
			<ymax>109</ymax>
		</bndbox>
	</object>
	<object>
		<name>no-mask</name>
		<pose>Unspecified</pose>
		<truncated>0</truncated>
		<difficult>0</difficult>
		<bndbox>
			<xmin>383</xmin>
			<ymin>75</ymin>
			<xmax>432</xmax>
			<ymax>140</ymax>
		</bndbox>
	</object>
</annotation>
